pdf2anki/__init__.py
pdf2anki/__main__.py
pdf2anki/config.py
pdf2anki/debug.py
pdf2anki/decorators.py
pdf2anki/elements.py
pdf2anki/evaluator.py
pdf2anki/extraction.py
pdf2anki/filters.py
pdf2anki/pdf2anki.py
pdf2anki/recipe.py
pdf2anki/stop_run.py
pdf2anki/utils.py
pdf2anki/tests/__init__.py
pdf2anki/tests/test_extraction.py
pdf2anki/tests/test_filters.py
pdf2anki/tests/test_recipe.py
pdf2anki/tests/test_utils.py
pdf2anki/tests/utils.py
mypdf2anki-0.1.0.dist-info/METADATA
mypdf2anki-0.1.0.dist-info/WHEEL
mypdf2anki-0.1.0.dist-info/entry_points.txt
mypdf2anki-0.1.0.dist-info/top_level.txt
mypdf2anki-0.1.0.dist-info/RECORD
